src/__init__.py
src/big_query.py
src/cloud_logging.py
src/cloud_storage.py
src/compute_engine.py
src/server.py
google_cloud_mcp-1.0.0.dist-info/METADATA
google_cloud_mcp-1.0.0.dist-info/WHEEL
google_cloud_mcp-1.0.0.dist-info/entry_points.txt
google_cloud_mcp-1.0.0.dist-info/licenses/LICENSE
google_cloud_mcp-1.0.0.dist-info/RECORD
