Metadata-Version: 2.4
Name: google-cloud-mcp
Version: 1.0.0
Summary: A comprehensive Model Context Protocol (MCP) server for Google Cloud Platform services including BigQuery, Cloud Logging, Cloud Storage, and Compute Engine.
Project-URL: Homepage, https://github.com/lockon-n/google-cloud-mcp
Project-URL: Repository, https://github.com/lockon-n/google-cloud-mcp
Project-URL: Documentation, https://github.com/lockon-n/google-cloud-mcp#readme
Project-URL: Issues, https://github.com/lockon-n/google-cloud-mcp/issues
Author: lockon-n
Maintainer: lockon-n
License: MIT
License-File: LICENSE
Keywords: ai,bigquery,cloud-logging,cloud-storage,compute-engine,fastmcp,gcp,google-cloud,mcp,model-context-protocol
Classifier: Development Status :: 5 - Production/Stable
Classifier: Intended Audience :: Developers
Classifier: License :: OSI Approved :: MIT License
Classifier: Operating System :: OS Independent
Classifier: Programming Language :: Python :: 3
Classifier: Programming Language :: Python :: 3.8
Classifier: Programming Language :: Python :: 3.9
Classifier: Programming Language :: Python :: 3.10
Classifier: Programming Language :: Python :: 3.11
Classifier: Programming Language :: Python :: 3.12
Classifier: Topic :: Internet
Classifier: Topic :: Software Development :: Libraries :: Python Modules
Classifier: Topic :: System :: Systems Administration
Requires-Python: >=3.8
Requires-Dist: fastmcp>=2.10.5
Requires-Dist: google-cloud-bigquery>=3.23.0
Requires-Dist: google-cloud-compute>=1.19.0
Requires-Dist: google-cloud-logging>=3.8.0
Requires-Dist: google-cloud-storage>=2.14.0
Requires-Dist: mcp[cli]>=1.11.0
Requires-Dist: pandas>=2.0.0
